dark_emulator/__init__.py
dark_emulator/darkemu/__init__.py
dark_emulator/darkemu/auto.py
dark_emulator/darkemu/cosmo_util.py
dark_emulator/darkemu/cross.py
dark_emulator/darkemu/de_interface.py
dark_emulator/darkemu/gamma1.py
dark_emulator/darkemu/hmf.py
dark_emulator/darkemu/pklin.py
dark_emulator/darkemu/sigmaM.py
dark_emulator/darkemu/sigmad.py
dark_emulator/darkemu/xinl.py
dark_emulator/darkemu/gp/__init__.py
dark_emulator/darkemu/gp/gp6d.py
dark_emulator/data/cparams_3d.dat
dark_emulator/data/cparams_4d.dat
dark_emulator/data/params.dat
dark_emulator/data/params_40x10.dat
dark_emulator/data/params_80models.dat
dark_emulator/data/scales.dat
dark_emulator/fftlog/__init__.py
dark_emulator/fftlog/fftlog.py
dark_emulator/learned_data/gamma1/coeff_all.npy
dark_emulator/learned_data/gamma1/gp6d_hyperparams.npy
dark_emulator/learned_data/gamma1/gp6d_kerneltype.npy
dark_emulator/learned_data/gamma1/pca_eigvec.npy
dark_emulator/learned_data/gamma1/yerr.npy
dark_emulator/learned_data/gamma1_dm/coeff_all.npy
dark_emulator/learned_data/gamma1_dm/gp6d_hyperparams.npy
dark_emulator/learned_data/gamma1_dm/gp6d_kerneltype.npy
dark_emulator/learned_data/gamma1_dm/pca_eigvec.npy
dark_emulator/learned_data/gamma1_dm/yerr.npy
dark_emulator/learned_data/hmf/coeff_all.npy
dark_emulator/learned_data/hmf/gp6d_hyperparams.npy
dark_emulator/learned_data/hmf/gp6d_kerneltype.npy
dark_emulator/learned_data/hmf/pca_eigvec.npy
dark_emulator/learned_data/hmf/yerr.npy
dark_emulator/learned_data/hmf/ymeans.npy
dark_emulator/learned_data/pklin/coeff_all.dat
dark_emulator/learned_data/pklin/gp_params.dat
dark_emulator/learned_data/pklin/ktypes.dat
dark_emulator/learned_data/pklin/pca_avg.dat
dark_emulator/learned_data/pklin/pca_eigvec.dat
dark_emulator/learned_data/pklin/pca_mean.dat
dark_emulator/learned_data/pklin/pca_std.dat
dark_emulator/learned_data/sigmaM/coeff_all.dat
dark_emulator/learned_data/sigmaM/gp_params.dat
dark_emulator/learned_data/sigmaM/ktypes.dat
dark_emulator-1.1.2.dist-info/LICENSE
dark_emulator-1.1.2.dist-info/METADATA
dark_emulator-1.1.2.dist-info/WHEEL
dark_emulator-1.1.2.dist-info/top_level.txt
dark_emulator-1.1.2.dist-info/RECORD
