Metadata-Version: 2.1
Name: dark_emulator
Version: 1.1.2
Summary: dark emulator package
Home-page: https://dark-emulator.readthedocs.io
Author: Takahiro Nishimichi, Hironao Miyatake, Sunao Sugiyama
Author-email: dark_emulator@ipmu.jp
Keywords: cosmology,large scale structure,halo,gaussian process,machine learning
Classifier: Programming Language :: Python :: 3
License-File: LICENSE
Requires-Dist: numpy
Requires-Dist: scipy
Requires-Dist: george
